{
  "lastUpdated": "2026-07-16 16:05 IST",
  "signals": [
    {
      "name": "GIFT Nifty",
      "value": 24072.8,
      "changePct": -0.02,
      "signal": "HOLD",
      "slot": "open",
      "source": "NSE IX (proxy: Nifty 50, Yahoo Finance)"
    },
    {
      "name": "Nasdaq Composite",
      "value": 26269.2,
      "changePct": 0.62,
      "signal": "BUY",
      "slot": "open",
      "source": "Yahoo Finance"
    },
    {
      "name": "Hang Seng",
      "value": 25008.6,
      "changePct": 1.33,
      "signal": "BUY",
      "slot": "open",
      "source": "Yahoo Finance"
    },
    {
      "name": "S&P 500",
      "value": 7572.4,
      "changePct": 0.38,
      "signal": "BUY",
      "slot": "open",
      "source": "Yahoo Finance"
    }
  ],
  "trackerYear": 2026,
  "trackerSource": "Algorithmic recommendations logged by brAInvest, marked-to-market with Yahoo Finance closes",
  "tracker": [
    {
      "month": "Jan",
      "actualPct": 66.47
    },
    {
      "month": "Feb",
      "actualPct": 23.95
    },
    {
      "month": "Mar",
      "actualPct": 15.29
    },
    {
      "month": "Apr",
      "actualPct": 56.97
    },
    {
      "month": "May",
      "actualPct": null
    },
    {
      "month": "Jun",
      "actualPct": -15.41
    },
    {
      "month": "Jul",
      "actualPct": null
    },
    {
      "month": "Aug",
      "actualPct": null
    },
    {
      "month": "Sep",
      "actualPct": null
    },
    {
      "month": "Oct",
      "actualPct": null
    },
    {
      "month": "Nov",
      "actualPct": null
    },
    {
      "month": "Dec",
      "actualPct": null
    }
  ],
  "monthlyTargetPct": 1.32
}